{
  "project_info": {
    "project_number": "455689471197",
    "firebase_url": "https://adujagokuis-bccdd.firebaseio.com",
    "project_id": "adujagokuis-bccdd",
    "storage_bucket": "adujagokuis-bccdd.appspot.com"
  },
  "client": [
    {
      "client_info": {
        "mobilesdk_app_id": "1:455689471197:android:5a8975a093c85fea",
        "android_client_info": {
          "package_name": "com.example.nicenicenice.projectpam"
        }
      },
      "oauth_client": [
        {
          "client_id": "455689471197-h43t0n8lhf3eabs64sl1g64d7cbo40s4.apps.googleusercontent.com",
          "client_type": 3
        }
      ],
      "api_key": [
        {
          "current_key": "AIzaSyDUr6aBdbyL4EH3upfhynTI56WC57DTGNU"
        }
      ],
      "services": {
        "analytics_service": {
          "status": 1
        },
        "appinvite_service": {
          "status": 1,
          "other_platform_oauth_client": []
        },
        "ads_service": {
          "status": 2
        }
      }
    }
  ],
  "configuration_version": "1"
}